RsCMX_Signaling/RsCMX_Signaling.py
RsCMX_Signaling/__init__.py
RsCMX_Signaling/enums.py
RsCMX_Signaling/repcap.py
RsCMX_Signaling/CustomFiles/__init__.py
RsCMX_Signaling/CustomFiles/events.py
RsCMX_Signaling/CustomFiles/reliability.py
RsCMX_Signaling/CustomFiles/utilities.py
RsCMX_Signaling/Implementations/__init__.py
RsCMX_Signaling/Implementations/Add/__init__.py
RsCMX_Signaling/Implementations/Add/Signaling/__init__.py
RsCMX_Signaling/Implementations/Add/Signaling/Eps/__init__.py
RsCMX_Signaling/Implementations/Add/Signaling/Eps/UeCapability/Eutra.py
RsCMX_Signaling/Implementations/Add/Signaling/Eps/UeCapability/Nradio.py
RsCMX_Signaling/Implementations/Add/Signaling/Eps/UeCapability/__init__.py
RsCMX_Signaling/Implementations/Add/Signaling/Eps/UeCapability/Mrdc/Bands.py
RsCMX_Signaling/Implementations/Add/Signaling/Eps/UeCapability/Mrdc/__init__.py
RsCMX_Signaling/Implementations/Add/Signaling/Fgs/__init__.py
RsCMX_Signaling/Implementations/Add/Signaling/Fgs/UeCapability/Eutra.py
RsCMX_Signaling/Implementations/Add/Signaling/Fgs/UeCapability/Nradio.py
RsCMX_Signaling/Implementations/Add/Signaling/Fgs/UeCapability/__init__.py
RsCMX_Signaling/Implementations/Add/Signaling/Fgs/UeCapability/Mrdc/Bands.py
RsCMX_Signaling/Implementations/Add/Signaling/Fgs/UeCapability/Mrdc/__init__.py
RsCMX_Signaling/Implementations/Add/Signaling/Lte/Ncell.py
RsCMX_Signaling/Implementations/Add/Signaling/Lte/__init__.py
RsCMX_Signaling/Implementations/Add/Signaling/Lte/Ca/Scell.py
RsCMX_Signaling/Implementations/Add/Signaling/Lte/Ca/__init__.py
RsCMX_Signaling/Implementations/Add/Signaling/Nradio/Ncell.py
RsCMX_Signaling/Implementations/Add/Signaling/Nradio/__init__.py
RsCMX_Signaling/Implementations/Add/Signaling/Nradio/Ca/Scell.py
RsCMX_Signaling/Implementations/Add/Signaling/Nradio/Ca/__init__.py
RsCMX_Signaling/Implementations/Add/Signaling/Nradio/Cell/Srs.py
RsCMX_Signaling/Implementations/Add/Signaling/Nradio/Cell/__init__.py
RsCMX_Signaling-4.0.120.dist-info/METADATA
RsCMX_Signaling-4.0.120.dist-info/WHEEL
RsCMX_Signaling-4.0.120.dist-info/top_level.txt
RsCMX_Signaling-4.0.120.dist-info/RECORD
